chat_completion_utils/__init__.py
chat_completion_utils/chat_utils.py
chat_completion_utils-1.2.5.dist-info/METADATA
chat_completion_utils-1.2.5.dist-info/WHEEL
chat_completion_utils-1.2.5.dist-info/RECORD
