Metadata-Version: 2.1
Name: chat-completion-utils
Version: 1.2.5
Summary: 
Author: estill01
Author-email: ehs.stillman@gmail.com
Requires-Python: >=3.9,<4.0
Classifier: Programming Language :: Python :: 3
Classifier: Programming Language :: Python :: 3.9
Classifier: Programming Language :: Python :: 3.10
Classifier: Programming Language :: Python :: 3.11
Requires-Dist: openai (>=0.27.4,<0.28.0)
Requires-Dist: tiktoken (>=0.3.3,<0.4.0)
